PyLiveRecorder/__init__.py
PyLiveRecorder/Core/Bilibili.py
PyLiveRecorder/Core/DouYu.py
PyLiveRecorder/Core/HuYa.py
PyLiveRecorder/Core/HuaJiao.py
PyLiveRecorder/Core/LongZhu.py
PyLiveRecorder/Core/YY.py
PyLiveRecorder/Core/YiZhiBo.py
PyLiveRecorder/Core/__init__.py
PyLiveRecorder/NoticeWare/Bilibili.py
PyLiveRecorder/NoticeWare/__init__.py
pyliverecorder-1.7.6.dist-info/LICENSE
pyliverecorder-1.7.6.dist-info/METADATA
pyliverecorder-1.7.6.dist-info/WHEEL
pyliverecorder-1.7.6.dist-info/top_level.txt
pyliverecorder-1.7.6.dist-info/RECORD
