Metadata-Version: 2.1
Name: pyliverecorder
Version: 1.7.6
Summary: Monitor the start of live and download media stream automatically.
Home-page: https://github.com/InJeCTrL/PyLiveRecorder/
Author: InJeCTrL
Author-email: dap1933@hotmail.com
License: MIT
Platform: UNKNOWN
License-File: LICENSE
Requires-Dist: requests
Requires-Dist: bs4
Requires-Dist: PyExecJS
